<?xml version="1.0" encoding="utf-8" ?>
<dwsync>
<file name="._.DS_Store" server="www.plazaindiantradingpost.com/tm/" local="131406290696148128" remote="131406675000000000" Dst="2" />
<file name="._dist" server="www.plazaindiantradingpost.com/tm/" local="131406290696343640" remote="131406675000000000" Dst="2" />
<file name="._docs" server="www.plazaindiantradingpost.com/tm/" local="131406290696584323" remote="131406675000000000" Dst="2" />
<file name="._js" server="www.plazaindiantradingpost.com/tm/" local="131406290697311213" remote="131406675000000000" Dst="2" />
<file name="._fonts" server="www.plazaindiantradingpost.com/tm/" local="131406290696854996" remote="131406675000000000" Dst="2" />
<file name="._gulpfile.js" server="www.plazaindiantradingpost.com/tm/" local="131406290697110683" remote="131406675000000000" Dst="2" />
<file name="._less" server="www.plazaindiantradingpost.com/tm/" local="131406290697501723" remote="131406675000000000" Dst="2" />
<file name="._README.md" server="www.plazaindiantradingpost.com/tm/" local="131406290697957940" remote="131406675000000000" Dst="2" />
<file name="._package.json" server="www.plazaindiantradingpost.com/tm/" local="131406290697757403" remote="131406675000000000" Dst="2" />
</dwsync>